pyo3_poker_eval-0.1.0.dist-info/top_level.txt
pyo3_poker_eval-0.1.0.dist-info/WHEEL
pyo3_poker_eval-0.1.0.dist-info/RECORD
pyo3_poker_eval-0.1.0.dist-info/METADATA
pyo3_poker_eval/__init__.py
pyo3_poker_eval/_rust.cpython-311-x86_64-linux-gnu.so
