Metadata-Version: 2.1
Name: pyo3_poker_eval
Version: 0.1.0
Summary: Poker eval library
Author-email: firstname lastname <author@gmail.com>
License: MIT
Project-URL: repository, https://github.com/oscar6echo/pyo3-poker-eval.git
Keywords: poker,rust
Classifier: Development Status :: 4 - Beta
Classifier: License :: OSI Approved :: MIT License
Classifier: Intended Audience :: Developers
Classifier: Programming Language :: Python :: 3
Classifier: Programming Language :: Python :: 3.10
Classifier: Programming Language :: Python :: 3.11
Classifier: Operating System :: POSIX
Classifier: Operating System :: MacOS :: MacOS X
Classifier: Operating System :: Microsoft :: Windows
Requires-Python: >=3.10
Provides-Extra: dev
Requires-Dist: pytest ; extra == 'dev'
